{"db_id": "agricultural_product_price_tracking", "ddls": ["CREATE TABLE \"units_of_measurement\" (\n  \"um_id\" INTEGER /* Unique identifier for each unit of measurement */,\n  \"um_name\" TEXT /* Name of the unit of measurement (e.g., KG) */,\n  \"um_description\" TEXT /* Description of the unit of measurement */,\n  PRIMARY KEY (\"um_id\")\n)", "CREATE TABLE \"product_categories\" (\n  \"category_id\" INTEGER /* Unique identifier for each product category */,\n  \"category_name\" TEXT /* Name of the product category (e.g., Grains) */,\n  \"category_description\" TEXT /* Description of the product category */,\n  PRIMARY KEY (\"category_id\")\n)", "CREATE TABLE \"products\" (\n  \"product_id\" INTEGER /* Unique identifier for each product */,\n  \"product_name\" TEXT /* Name of the product (e.g., Rice - Retail) */,\n  \"category_id\" INTEGER /* ID of the product category */,\n  \"um_id\" INTEGER /* ID of the unit of measurement for the product */,\n  PRIMARY KEY (\"product_id\"), \n  CONSTRAINT fk_products_um_id FOREIGN KEY (\"um_id\") REFERENCES units_of_measurement (\"um_id\"), \n  CONSTRAINT fk_products_category_id FOREIGN KEY (\"category_id\") REFERENCES product_categories (\"category_id\")\n)", "CREATE TABLE \"regions\" (\n  \"region_id\" INTEGER /* Unique identifier for each region */,\n  \"region_name\" TEXT /* Name of the region (e.g., National Average) */,\n  \"region_type\" TEXT /* Type of region (e.g., National, State, City) */,\n  PRIMARY KEY (\"region_id\")\n)", "CREATE TABLE \"price_records\" (\n  \"price_id\" INTEGER /* Unique identifier for each price record */,\n  \"product_id\" INTEGER /* ID of the product the price belongs to */,\n  \"region_id\" INTEGER /* ID of the region where the price was recorded */,\n  \"month\" INTEGER /* Month the price was recorded */,\n  \"year\" INTEGER /* Year the price was recorded */,\n  \"price\" REAL /* Price value */,\n  PRIMARY KEY (\"price_id\"), \n  CONSTRAINT fk_price_records_product_id FOREIGN KEY (\"product_id\") REFERENCES products (\"product_id\"), \n  CONSTRAINT fk_price_records_region_id FOREIGN KEY (\"region_id\") REFERENCES regions (\"region_id\")\n)", "CREATE TABLE \"price_change_records\" (\n  \"price_change_id\" INTEGER /* Unique identifier for each price change record */,\n  \"price_id\" INTEGER /* ID of the price record */,\n  \"month\" INTEGER /* Month the price change occurred */,\n  \"year\" INTEGER /* Year the price change occurred */,\n  \"price_change\" REAL /* Price change value */,\n  PRIMARY KEY (\"price_change_id\"), \n  CONSTRAINT fk_price_change_records_price_id FOREIGN KEY (\"price_id\") REFERENCES price_records (\"price_id\")\n)"], "column_names": [[-1, "*"], [0, "Unique identifier for each unit of measurement"], [0, "Name of the unit of measurement (e.g., KG)"], [0, "Description of the unit of measurement"], [1, "Unique identifier for each product category"], [1, "Name of the product category (e.g., Grains)"], [1, "Description of the product category"], [2, "Unique identifier for each product"], [2, "Name of the product (e.g., Rice - Retail)"], [2, "ID of the product category"], [2, "ID of the unit of measurement for the product"], [3, "Unique identifier for each region"], [3, "Name of the region (e.g., National Average)"], [3, "Type of region (e.g., National, State, City)"], [4, "Unique identifier for each price record"], [4, "ID of the product the price belongs to"], [4, "ID of the region where the price was recorded"], [4, "Month the price was recorded"], [4, "Year the price was recorded"], [4, "Price value"], [5, "Unique identifier for each price change record"], [5, "ID of the price record"], [5, "Month the price change occurred"], [5, "Year the price change occurred"], [5, "Price change value"]], "column_names_original": [[-1, "*"], [0, "um_id"], [0, "um_name"], [0, "um_description"], [1, "category_id"], [1, "category_name"], [1, "category_description"], [2, "product_id"], [2, "product_name"], [2, "category_id"], [2, "um_id"], [3, "region_id"], [3, "region_name"], [3, "region_type"], [4, "price_id"], [4, "product_id"], [4, "region_id"], [4, "month"], [4, "year"], [4, "price"], [5, "price_change_id"], [5, "price_id"], [5, "month"], [5, "year"], [5, "price_change"]], "column_types": ["text", "INTEGER", "TEXT", "TEXT", "INTEGER", "TEXT", "TEXT", "INTEGER", "TEXT", "INTEGER", "INTEGER", "INTEGER", "TEXT", "TEXT", "INTEGER", "INTEGER", "INTEGER", "INTEGER", "INTEGER", "REAL", "INTEGER", "INTEGER", "INTEGER", "INTEGER", "REAL"], "table_names": ["units_of_measurement", "product_categories", "products", "regions", "price_records", "price_change_records"], "table_names_original": ["units_of_measurement", "product_categories", "products", "regions", "price_records", "price_change_records"], "foreign_keys": [[9, 4], [10, 1], [16, 11], [15, 7], [21, 14]], "primary_keys": [1, 4, 7, 11, 14, 20]}