{"db_id": "automotive_pricing_and_power_statistics", "ddls": ["CREATE TABLE \"vehicle_statistics\" (\n  \"stat_id\" INTEGER /* Unique identifier for each statistical entry */,\n  \"model_id\" INTEGER /* Reference to the vehicle model */,\n  \"count\" INTEGER /* Number of vehicles represented in this entry */,\n  \"km\" INTEGER /* Average kilometers driven by the vehicles */,\n  \"year\" INTEGER /* Year of the statistical data */,\n  \"powerPS\" INTEGER /* Power output of vehicles in PS (Pferdestärke) */,\n  \"minPrice\" REAL /* Minimum price of the vehicles */,\n  \"maxPrice\" REAL /* Maximum price of the vehicles */,\n  \"avgPrice\" REAL /* Average price of the vehicles */,\n  \"sdPrice\" REAL /* Standard deviation of prices */,\n  \"fuel_type\" TEXT /* Type of fuel used by the vehicle */,\n  \"transmission_type\" TEXT /* Type of transmission */,\n  \"body_type\" TEXT /* Body type of the vehicle */,\n  \"emissions\" REAL /* CO2 emissions of the vehicle */,\n  \"last_updated\" TEXT /* Timestamp of when the statistical data was last updated */,\n  PRIMARY KEY (\"stat_id\"), \n  CONSTRAINT fk_vehicle_statistics_model_id FOREIGN KEY (\"model_id\") REFERENCES vehicle_models (\"model_id\")\n)", "CREATE TABLE \"vehicle_models\" (\n  \"model_id\" INTEGER /* Unique identifier for each vehicle model */,\n  \"model_name\" TEXT /* Name of the vehicle model */,\n  \"manufacturer\" TEXT /* Manufacturer of the vehicle */,\n  \"year_introduced\" INTEGER /* The year the vehicle model was introduced */,\n  \"fuel_type\" TEXT /* Type of fuel used by the model */,\n  \"transmission_type\" TEXT /* Type of transmission for the model */,\n  \"body_type\" TEXT /* Body type of the model */,\n  \"emissions\" REAL /* Average CO2 emissions for the model */,\n  \"horsepower_range\" TEXT /* Range of horsepower for the model */,\n  \"mileage_range\" TEXT /* Range of average kilometers driven for the model */,\n  \"last_updated\" TEXT /* Timestamp of when the model information was last updated */,\n  PRIMARY KEY (\"model_id\")\n)", "CREATE TABLE \"pricing_history\" (\n  \"price_id\" INTEGER /* Unique identifier for each price record */,\n  \"model_id\" INTEGER /* Reference to the vehicle model */,\n  \"year\" INTEGER /* Year of the recorded price */,\n  \"price\" REAL /* Price of the vehicle model in the given year */,\n  \"source\" TEXT /* Source of the price data */,\n  \"condition\" TEXT /* Condition of the vehicle */,\n  \"mileage\" INTEGER /* Mileage of the vehicle at the time of pricing */,\n  \"location\" TEXT /* Geographic location of the price data */,\n  \"last_updated\" TEXT /* Timestamp of when the price record was last updated */,\n  PRIMARY KEY (\"price_id\"), \n  CONSTRAINT fk_pricing_history_model_id FOREIGN KEY (\"model_id\") REFERENCES vehicle_models (\"model_id\")\n)"], "column_names": [[-1, "*"], [0, "Unique identifier for each statistical entry"], [0, "Reference to the vehicle model"], [0, "Number of vehicles represented in this entry"], [0, "Average kilometers driven by the vehicles"], [0, "Year of the statistical data"], [0, "Power output of vehicles in PS (Pferdestärke)"], [0, "Minimum price of the vehicles"], [0, "Maximum price of the vehicles"], [0, "Average price of the vehicles"], [0, "Standard deviation of prices"], [0, "Type of fuel used by the vehicle"], [0, "Type of transmission"], [0, "Body type of the vehicle"], [0, "CO2 emissions of the vehicle"], [0, "Timestamp of when the statistical data was last updated"], [1, "Unique identifier for each vehicle model"], [1, "Name of the vehicle model"], [1, "Manufacturer of the vehicle"], [1, "The year the vehicle model was introduced"], [1, "Type of fuel used by the model"], [1, "Type of transmission for the model"], [1, "Body type of the model"], [1, "Average CO2 emissions for the model"], [1, "Range of horsepower for the model"], [1, "Range of average kilometers driven for the model"], [1, "Timestamp of when the model information was last updated"], [2, "Unique identifier for each price record"], [2, "Reference to the vehicle model"], [2, "Year of the recorded price"], [2, "Price of the vehicle model in the given year"], [2, "Source of the price data"], [2, "Condition of the vehicle"], [2, "Mileage of the vehicle at the time of pricing"], [2, "Geographic location of the price data"], [2, "Timestamp of when the price record was last updated"]], "column_names_original": [[-1, "*"], [0, "stat_id"], [0, "model_id"], [0, "count"], [0, "km"], [0, "year"], [0, "powerPS"], [0, "minPrice"], [0, "maxPrice"], [0, "avgPrice"], [0, "sdPrice"], [0, "fuel_type"], [0, "transmission_type"], [0, "body_type"], [0, "emissions"], [0, "last_updated"], [1, "model_id"], [1, "model_name"], [1, "manufacturer"], [1, "year_introduced"], [1, "fuel_type"], [1, "transmission_type"], [1, "body_type"], [1, "emissions"], [1, "horsepower_range"], [1, "mileage_range"], [1, "last_updated"], [2, "price_id"], [2, "model_id"], [2, "year"], [2, "price"], [2, "source"], [2, "condition"], [2, "mileage"], [2, "location"], [2, "last_updated"]], "column_types": ["text", "INTEGER", "INTEGER", "INTEGER", "INTEGER", "INTEGER", "INTEGER", "REAL", "REAL", "REAL", "REAL", "TEXT", "TEXT", "TEXT", "REAL", "TEXT", "INTEGER", "TEXT", "TEXT", "INTEGER", "TEXT", "TEXT", "TEXT", "REAL", "TEXT", "TEXT", "TEXT", "INTEGER", "INTEGER", "INTEGER", "REAL", "TEXT", "TEXT", "INTEGER", "TEXT", "TEXT"], "table_names": ["vehicle_statistics", "vehicle_models", "pricing_history"], "table_names_original": ["vehicle_statistics", "vehicle_models", "pricing_history"], "foreign_keys": [[2, 16], [28, 16]], "primary_keys": [1, 16, 27]}