{"db_id": "corporate_financial_reporting_and_shareholder_equity_management", "ddls": ["CREATE TABLE \"financial_periods\" (\n  \"period_id\" INTEGER /* Unique identifier for each financial period */,\n  \"start_date\" TEXT /* Start date of the financial period */,\n  \"end_date\" TEXT /* End date of the financial period */,\n  \"period_type\" TEXT /* Type of financial period (e.g., quarterly, annual) */,\n  \"fiscal_year\" INTEGER /* Fiscal year of the financial period */,\n  \"is_closed\" INTEGER /* Flag indicating if the period is closed */,\n  \"created_at\" TEXT /* Timestamp of when the financial period was created */,\n  \"updated_at\" TEXT /* Timestamp of the last update to the financial period */,\n  PRIMARY KEY (\"period_id\")\n)", "CREATE TABLE \"shareholders_equity\" (\n  \"equity_id\" INTEGER /* Unique identifier for each shareholders' equity entry */,\n  \"period_id\" INTEGER /* ID of the financial period */,\n  \"ordinary_shares\" TEXT /* Value of ordinary shares */,\n  \"additional_paid_in_capital\" TEXT /* Value of additional paid-in capital */,\n  \"accumulated_deficit\" TEXT /* Value of accumulated deficit */,\n  \"total\" TEXT /* Total value of shareholders' equity */,\n  \"beginning_balance\" TEXT /* Balance at the beginning of the period */,\n  \"ending_balance\" TEXT /* Balance at the end of the period */,\n  \"net_income_loss\" TEXT /* Net income or loss for the period */,\n  \"created_at\" TEXT /* Timestamp of when the shareholders' equity entry was created */,\n  \"updated_at\" TEXT /* Timestamp of the last update to the shareholders' equity entry */,\n  PRIMARY KEY (\"equity_id\"), \n  CONSTRAINT fk_shareholders_equity_period_id FOREIGN KEY (\"period_id\") REFERENCES financial_periods (\"period_id\")\n)", "CREATE TABLE \"financial_components\" (\n  \"component_id\" INTEGER /* Unique identifier for each financial component */,\n  \"equity_id\" INTEGER /* ID of the shareholders' equity entry */,\n  \"component_type\" TEXT /* Type of financial component (e.g., net loss, adjustment to ordinary shares) */,\n  \"value\" TEXT /* Value of the financial component */,\n  \"description\" TEXT /* Description of the financial component */,\n  \"created_at\" TEXT /* Timestamp of when the financial component was created */,\n  \"updated_at\" TEXT /* Timestamp of the last update to the financial component */,\n  PRIMARY KEY (\"component_id\"), \n  CONSTRAINT fk_financial_components_equity_id FOREIGN KEY (\"equity_id\") REFERENCES shareholders_equity (\"equity_id\")\n)", "CREATE TABLE \"users\" (\n  \"user_id\" INTEGER /* Unique identifier for each user */,\n  \"user_name\" TEXT /* Full name of the user */,\n  \"email\" TEXT /* Email address of the user */,\n  \"role\" TEXT /* Role of the user (e.g., financial analyst, accountant, executive) */,\n  \"password_hash\" TEXT /* Hashed password of the user */,\n  \"last_login\" TEXT /* Timestamp of the user's last login */,\n  \"created_at\" TEXT /* Timestamp of when the user account was created */,\n  \"updated_at\" TEXT /* Timestamp of the last update to the user account */,\n  PRIMARY KEY (\"user_id\")\n)"], "column_names": [[-1, "*"], [0, "Unique identifier for each financial period"], [0, "Start date of the financial period"], [0, "End date of the financial period"], [0, "Type of financial period (e.g., quarterly, annual)"], [0, "Fiscal year of the financial period"], [0, "Flag indicating if the period is closed"], [0, "Timestamp of when the financial period was created"], [0, "Timestamp of the last update to the financial period"], [1, "Unique identifier for each shareholders' equity entry"], [1, "ID of the financial period"], [1, "Value of ordinary shares"], [1, "Value of additional paid-in capital"], [1, "Value of accumulated deficit"], [1, "Total value of shareholders' equity"], [1, "Balance at the beginning of the period"], [1, "Balance at the end of the period"], [1, "Net income or loss for the period"], [1, "Timestamp of when the shareholders' equity entry was created"], [1, "Timestamp of the last update to the shareholders' equity entry"], [2, "Unique identifier for each financial component"], [2, "ID of the shareholders' equity entry"], [2, "Type of financial component (e.g., net loss, adjustment to ordinary shares)"], [2, "Value of the financial component"], [2, "Description of the financial component"], [2, "Timestamp of when the financial component was created"], [2, "Timestamp of the last update to the financial component"], [3, "Unique identifier for each user"], [3, "Full name of the user"], [3, "Email address of the user"], [3, "Role of the user (e.g., financial analyst, accountant, executive)"], [3, "Hashed password of the user"], [3, "Timestamp of the user's last login"], [3, "Timestamp of when the user account was created"], [3, "Timestamp of the last update to the user account"]], "column_names_original": [[-1, "*"], [0, "period_id"], [0, "start_date"], [0, "end_date"], [0, "period_type"], [0, "fiscal_year"], [0, "is_closed"], [0, "created_at"], [0, "updated_at"], [1, "equity_id"], [1, "period_id"], [1, "ordinary_shares"], [1, "additional_paid_in_capital"], [1, "accumulated_deficit"], [1, "total"], [1, "beginning_balance"], [1, "ending_balance"], [1, "net_income_loss"], [1, "created_at"], [1, "updated_at"], [2, "component_id"], [2, "equity_id"], [2, "component_type"], [2, "value"], [2, "description"], [2, "created_at"], [2, "updated_at"], [3, "user_id"], [3, "user_name"], [3, "email"], [3, "role"], [3, "password_hash"], [3, "last_login"], [3, "created_at"], [3, "updated_at"]], "column_types": ["text", "INTEGER", "TEXT", "TEXT", "TEXT", "INTEGER", "INTEGER", "TEXT", "TEXT", "INTEGER", "INTEGER", "TEXT", "TEXT", "TEXT", "TEXT", "TEXT", "TEXT", "TEXT", "TEXT", "TEXT", "INTEGER", "INTEGER", "TEXT", "TEXT", "TEXT", "TEXT", "TEXT", "INTEGER", "TEXT", "TEXT", "TEXT", "TEXT", "TEXT", "TEXT", "TEXT"], "table_names": ["financial_periods", "shareholders_equity", "financial_components", "users"], "table_names_original": ["financial_periods", "shareholders_equity", "financial_components", "users"], "foreign_keys": [[10, 1], [21, 9]], "primary_keys": [1, 9, 20, 27]}