{"db_id": "demographic_data_analysis_and_income_prediction", "ddls": ["CREATE TABLE \"occupations\" (\n  \"occupation_id\" INTEGER /* Unique identifier for each occupation */,\n  \"occupation_name\" TEXT /* Name of the occupation */,\n  \"description\" TEXT /* Description of the occupation */,\n  \"median_income\" INTEGER /* Median income for the occupation */,\n  \"growth_rate\" REAL /* Growth rate of the occupation */,\n  \"is_in_demand\" INTEGER /* Indicates if the occupation is in high demand */,\n  \"last_updated\" TEXT /* Date and time when the record was last updated */,\n  \"created_by\" INTEGER /* ID of the user who created the record */,\n  \"updated_by\" INTEGER /* ID of the user who last updated the record */,\n  PRIMARY KEY (\"occupation_id\")\n)", "CREATE TABLE \"income_levels\" (\n  \"income_level_id\" INTEGER /* Unique identifier for each income level category */,\n  \"income_category\" TEXT /* Income category (<=50K or >50K) */,\n  \"description\" TEXT /* Description of the income level category */,\n  \"percentage_population\" REAL /* Percentage of the population in this income category */,\n  \"median_age\" INTEGER /* Median age of individuals in this income category */,\n  \"median_education_num\" INTEGER /* Median education level of individuals in this income category */,\n  \"last_updated\" TEXT /* Date and time when the record was last updated */,\n  \"created_by\" INTEGER /* ID of the user who created the record */,\n  \"updated_by\" INTEGER /* ID of the user who last updated the record */,\n  PRIMARY KEY (\"income_level_id\")\n)"], "column_names": [[-1, "*"], [0, "Unique identifier for each occupation"], [0, "Name of the occupation"], [0, "Description of the occupation"], [0, "Median income for the occupation"], [0, "Growth rate of the occupation"], [0, "Indicates if the occupation is in high demand"], [0, "Date and time when the record was last updated"], [0, "ID of the user who created the record"], [0, "ID of the user who last updated the record"], [1, "Unique identifier for each income level category"], [1, "Income category (<=50K or >50K)"], [1, "Description of the income level category"], [1, "Percentage of the population in this income category"], [1, "Median age of individuals in this income category"], [1, "Median education level of individuals in this income category"], [1, "Date and time when the record was last updated"], [1, "ID of the user who created the record"], [1, "ID of the user who last updated the record"]], "column_names_original": [[-1, "*"], [0, "occupation_id"], [0, "occupation_name"], [0, "description"], [0, "median_income"], [0, "growth_rate"], [0, "is_in_demand"], [0, "last_updated"], [0, "created_by"], [0, "updated_by"], [1, "income_level_id"], [1, "income_category"], [1, "description"], [1, "percentage_population"], [1, "median_age"], [1, "median_education_num"], [1, "last_updated"], [1, "created_by"], [1, "updated_by"]], "column_types": ["text", "INTEGER", "TEXT", "TEXT", "INTEGER", "REAL", "INTEGER", "TEXT", "INTEGER", "INTEGER", "INTEGER", "TEXT", "TEXT", "REAL", "INTEGER", "INTEGER", "TEXT", "INTEGER", "INTEGER"], "table_names": ["occupations", "income_levels"], "table_names_original": ["occupations", "income_levels"], "foreign_keys": [], "primary_keys": [1, 10]}