{"db_id": "economic_and_oil_price_analysis", "ddls": ["CREATE TABLE \"economic_data\" (\n  \"data_id\" INTEGER /* Unique identifier for each data point */,\n  \"quarter\" TEXT /* Quarter of the year (e.g., 1971q1, 1971q2) */,\n  \"year\" INTEGER /* Year of the quarter */,\n  \"gdp\" TEXT /* GDP value for the quarter */,\n  \"cpi\" TEXT /* CPI value for the quarter */,\n  \"stn\" TEXT /* Short-term interest rate (STN) for the quarter */,\n  \"country\" TEXT /* Country of the data */,\n  \"data_source\" TEXT /* Source of the data */,\n  \"created_at\" TEXT /* Timestamp when the data was created */,\n  \"updated_at\" TEXT /* Timestamp of the last update */,\n  \"version\" TEXT /* Version of the data */,\n  PRIMARY KEY (\"data_id\")\n)", "CREATE TABLE \"oil_prices\" (\n  \"price_id\" INTEGER /* Unique identifier for each oil price data point */,\n  \"quarter\" TEXT /* Quarter of the year (e.g., 1971q1, 1971q2) */,\n  \"year\" INTEGER /* Year of the quarter */,\n  \"oil_price\" TEXT /* Oil price for the quarter */,\n  \"country\" TEXT /* Country of the data */,\n  \"oil_type\" TEXT /* Type of oil (e.g., Brent, WTI) */,\n  \"data_source\" TEXT /* Source of the data */,\n  \"created_at\" TEXT /* Timestamp when the data was created */,\n  \"updated_at\" TEXT /* Timestamp of the last update */,\n  \"version\" TEXT /* Version of the data */,\n  PRIMARY KEY (\"price_id\"), \n  CONSTRAINT fk_oil_prices_quarter FOREIGN KEY (\"quarter\") REFERENCES economic_data (\"quarter\")\n)", "CREATE TABLE \"users\" (\n  \"user_id\" INTEGER /* Unique identifier for each user */,\n  \"user_name\" TEXT /* Full name of the user */,\n  \"email\" TEXT /* Email address of the user */,\n  \"role\" TEXT /* Role of the user (e.g., researcher, analyst) */,\n  \"department\" TEXT /* Department of the user (e.g., Research, Analytics) */,\n  \"created_at\" TEXT /* Timestamp when the user account was created */,\n  \"last_login\" TEXT /* Timestamp of the last login */,\n  \"status\" TEXT /* Status of the user account (e.g., active, suspended) */,\n  PRIMARY KEY (\"user_id\")\n)", "CREATE TABLE \"access_logs\" (\n  \"access_id\" INTEGER /* Unique identifier for each access event */,\n  \"data_id\" INTEGER /* ID of the economic data being accessed */,\n  \"user_id\" INTEGER /* ID of the user accessing the data */,\n  \"access_date\" TEXT /* Date when the data was accessed */,\n  \"access_type\" TEXT /* Type of access (e.g., view, download) */,\n  \"ip_address\" TEXT /* IP address from which the access was made */,\n  \"device\" TEXT /* Device used for access (e.g., desktop, mobile) */,\n  \"user_agent\" TEXT /* User agent string for the access request */,\n  \"data_version\" TEXT /* Version of the data accessed */,\n  PRIMARY KEY (\"access_id\"), \n  CONSTRAINT fk_access_logs_data_id FOREIGN KEY (\"data_id\") REFERENCES economic_data (\"data_id\"), \n  CONSTRAINT fk_access_logs_user_id FOREIGN KEY (\"user_id\") REFERENCES users (\"user_id\")\n)"], "column_names": [[-1, "*"], [0, "Unique identifier for each data point"], [0, "Quarter of the year (e.g., 1971q1, 1971q2)"], [0, "Year of the quarter"], [0, "GDP value for the quarter"], [0, "CPI value for the quarter"], [0, "Short-term interest rate (STN) for the quarter"], [0, "Country of the data"], [0, "Source of the data"], [0, "Timestamp when the data was created"], [0, "Timestamp of the last update"], [0, "Version of the data"], [1, "Unique identifier for each oil price data point"], [1, "Quarter of the year (e.g., 1971q1, 1971q2)"], [1, "Year of the quarter"], [1, "Oil price for the quarter"], [1, "Country of the data"], [1, "Type of oil (e.g., Brent, WTI)"], [1, "Source of the data"], [1, "Timestamp when the data was created"], [1, "Timestamp of the last update"], [1, "Version of the data"], [2, "Unique identifier for each user"], [2, "Full name of the user"], [2, "Email address of the user"], [2, "Role of the user (e.g., researcher, analyst)"], [2, "Department of the user (e.g., Research, Analytics)"], [2, "Timestamp when the user account was created"], [2, "Timestamp of the last login"], [2, "Status of the user account (e.g., active, suspended)"], [3, "Unique identifier for each access event"], [3, "ID of the economic data being accessed"], [3, "ID of the user accessing the data"], [3, "Date when the data was accessed"], [3, "Type of access (e.g., view, download)"], [3, "IP address from which the access was made"], [3, "Device used for access (e.g., desktop, mobile)"], [3, "User agent string for the access request"], [3, "Version of the data accessed"]], "column_names_original": [[-1, "*"], [0, "data_id"], [0, "quarter"], [0, "year"], [0, "gdp"], [0, "cpi"], [0, "stn"], [0, "country"], [0, "data_source"], [0, "created_at"], [0, "updated_at"], [0, "version"], [1, "price_id"], [1, "quarter"], [1, "year"], [1, "oil_price"], [1, "country"], [1, "oil_type"], [1, "data_source"], [1, "created_at"], [1, "updated_at"], [1, "version"], [2, "user_id"], [2, "user_name"], [2, "email"], [2, "role"], [2, "department"], [2, "created_at"], [2, "last_login"], [2, "status"], [3, "access_id"], [3, "data_id"], [3, "user_id"], [3, "access_date"], [3, "access_type"], [3, "ip_address"], [3, "device"], [3, "user_agent"], [3, "data_version"]], "column_types": ["text", "INTEGER", "TEXT", "INTEGER", "TEXT", "TEXT", "TEXT", "TEXT", "TEXT", "TEXT", "TEXT", "TEXT", "INTEGER", "TEXT", "INTEGER", "TEXT", "TEXT", "TEXT", "TEXT", "TEXT", "TEXT", "TEXT", "INTEGER", "TEXT", "TEXT", "TEXT", "TEXT", "TEXT", "TEXT", "TEXT", "INTEGER", "INTEGER", "INTEGER", "TEXT", "TEXT", "TEXT", "TEXT", "TEXT", "TEXT"], "table_names": ["economic_data", "oil_prices", "users", "access_logs"], "table_names_original": ["economic_data", "oil_prices", "users", "access_logs"], "foreign_keys": [[13, 2], [32, 22], [31, 1]], "primary_keys": [1, 12, 22, 30]}