{"db_id": "physics_simulation_data_management", "ddls": ["CREATE TABLE \"simulations\" (\n  \"simulation_id\" INTEGER /* Unique identifier for each simulation run */,\n  \"name\" TEXT /* Name of the simulation run */,\n  \"description\" TEXT /* Description of the simulation run */,\n  \"start_time\" TEXT /* Start time of the simulation */,\n  \"end_time\" TEXT /* End time of the simulation */,\n  \"parameters\" TEXT /* Parameters used in the simulation (e.g., gravity, friction coefficients) */,\n  \"initial_conditions\" TEXT /* Initial conditions of the simulation (e.g., initial positions, velocities) */,\n  \"project_id\" INTEGER /* ID of the project to which the simulation belongs */,\n  \"status\" TEXT /* Current status of the simulation (e.g., running, completed, failed) */,\n  \"created_by\" INTEGER /* User who created the simulation */,\n  \"last_updated_by\" INTEGER /* User who last updated the simulation */,\n  \"last_updated_time\" TEXT /* Timestamp of the last update */,\n  PRIMARY KEY (\"simulation_id\"), \n  CONSTRAINT fk_simulations_created_by FOREIGN KEY (\"created_by\") REFERENCES users (\"user_id\"), \n  CONSTRAINT fk_simulations_last_updated_by FOREIGN KEY (\"last_updated_by\") REFERENCES users (\"user_id\")\n)", "CREATE TABLE \"simulation_data\" (\n  \"data_id\" INTEGER /* Unique identifier for each data point */,\n  \"simulation_id\" INTEGER /* ID of the simulation run the data belongs to */,\n  \"node_idx\" INTEGER /* Index of the node in the simulation */,\n  \"x\" REAL /* Position of the node */,\n  \"v\" REAL /* Velocity of the node */,\n  \"theta\" REAL /* Angle of the node */,\n  \"omega\" REAL /* Angular velocity of the node */,\n  \"force\" REAL /* Force applied to the node */,\n  \"time\" REAL /* Time at which the data point was recorded */,\n  \"node_type\" TEXT /* Type of node (e.g., mechanical, electrical) */,\n  \"node_description\" TEXT /* Description of the node */,\n  \"node_properties\" TEXT /* Additional properties of the node (e.g., mass, length) */,\n  \"data_version\" INTEGER /* Version of the data */,\n  \"data_source\" TEXT /* Source of the data (e.g., simulation, experiment) */,\n  PRIMARY KEY (\"data_id\"), \n  CONSTRAINT fk_simulation_data_simulation_id FOREIGN KEY (\"simulation_id\") REFERENCES simulations (\"simulation_id\")\n)", "CREATE TABLE \"users\" (\n  \"user_id\" INTEGER /* Unique identifier for each user */,\n  \"user_name\" TEXT /* Full name of the user */,\n  \"email\" TEXT /* Email address of the user */,\n  \"role\" TEXT /* Role of the user (e.g., researcher, data analyst, admin) */,\n  \"project_id\" INTEGER /* ID of the project to which the user belongs */,\n  \"affiliation\" TEXT /* Affiliation of the user (e.g., university, company) */,\n  \"contact_number\" TEXT /* Contact number of the user */,\n  \"created_at\" TEXT /* Timestamp when the user account was created */,\n  PRIMARY KEY (\"user_id\")\n)"], "column_names": [[-1, "*"], [0, "Unique identifier for each simulation run"], [0, "Name of the simulation run"], [0, "Description of the simulation run"], [0, "Start time of the simulation"], [0, "End time of the simulation"], [0, "Parameters used in the simulation (e.g., gravity, friction coefficients)"], [0, "Initial conditions of the simulation (e.g., initial positions, velocities)"], [0, "ID of the project to which the simulation belongs"], [0, "Current status of the simulation (e.g., running, completed, failed)"], [0, "User who created the simulation"], [0, "User who last updated the simulation"], [0, "Timestamp of the last update"], [1, "Unique identifier for each data point"], [1, "ID of the simulation run the data belongs to"], [1, "Index of the node in the simulation"], [1, "Position of the node"], [1, "Velocity of the node"], [1, "Angle of the node"], [1, "Angular velocity of the node"], [1, "Force applied to the node"], [1, "Time at which the data point was recorded"], [1, "Type of node (e.g., mechanical, electrical)"], [1, "Description of the node"], [1, "Additional properties of the node (e.g., mass, length)"], [1, "Version of the data"], [1, "Source of the data (e.g., simulation, experiment)"], [2, "Unique identifier for each user"], [2, "Full name of the user"], [2, "Email address of the user"], [2, "Role of the user (e.g., researcher, data analyst, admin)"], [2, "ID of the project to which the user belongs"], [2, "Affiliation of the user (e.g., university, company)"], [2, "Contact number of the user"], [2, "Timestamp when the user account was created"]], "column_names_original": [[-1, "*"], [0, "simulation_id"], [0, "name"], [0, "description"], [0, "start_time"], [0, "end_time"], [0, "parameters"], [0, "initial_conditions"], [0, "project_id"], [0, "status"], [0, "created_by"], [0, "last_updated_by"], [0, "last_updated_time"], [1, "data_id"], [1, "simulation_id"], [1, "node_idx"], [1, "x"], [1, "v"], [1, "theta"], [1, "omega"], [1, "force"], [1, "time"], [1, "node_type"], [1, "node_description"], [1, "node_properties"], [1, "data_version"], [1, "data_source"], [2, "user_id"], [2, "user_name"], [2, "email"], [2, "role"], [2, "project_id"], [2, "affiliation"], [2, "contact_number"], [2, "created_at"]], "column_types": ["text", "INTEGER", "TEXT", "TEXT", "TEXT", "TEXT", "TEXT", "TEXT", "INTEGER", "TEXT", "INTEGER", "INTEGER", "TEXT", "INTEGER", "INTEGER", "INTEGER", "REAL", "REAL", "REAL", "REAL", "REAL", "REAL", "TEXT", "TEXT", "TEXT", "INTEGER", "TEXT", "INTEGER", "TEXT", "TEXT", "TEXT", "INTEGER", "TEXT", "TEXT", "TEXT"], "table_names": ["simulations", "simulation_data", "users"], "table_names_original": ["simulations", "simulation_data", "users"], "foreign_keys": [[11, 27], [10, 27], [14, 1]], "primary_keys": [1, 13, 27]}