{"db_id": "environmental_monitoring_and_site_tracking", "ddls": ["CREATE TABLE \"site_attributes\" (\n  \"attribute_id\" INTEGER /* Unique identifier for each attribute record */,\n  \"site_id\" INTEGER /* Foreign key referencing the monitoring_sites table */,\n  \"attribute_name\" TEXT /* Name of the attribute being tracked */,\n  \"attribute_value\" TEXT /* Value of the attribute at a specific point in time */,\n  \"recorded_at\" TEXT /* Timestamp indicating when the attribute value was recorded */,\n  \"units\" TEXT /* Unit of measurement for the attribute value */,\n  PRIMARY KEY (\"attribute_id\")\n)", "CREATE TABLE \"site_readings\" (\n  \"reading_id\" INTEGER /* Unique identifier for each reading record */,\n  \"site_id\" INTEGER /* Foreign key referencing the monitoring_sites table */,\n  \"reading_date\" TEXT /* Timestamp indicating when the reading was taken */,\n  \"parameter\" TEXT /* Parameter being measured */,\n  \"value\" TEXT /* Value of the parameter at the time of the reading */,\n  \"units\" TEXT /* Unit of measurement for the parameter value */,\n  PRIMARY KEY (\"reading_id\")\n)", "CREATE TABLE \"regions\" (\n  \"region_id\" INTEGER /* Unique identifier for each region */,\n  \"region_name\" TEXT /* Name of the region */,\n  \"description\" TEXT /* Brief description of the region */,\n  \"ct\" TEXT /* Country abbreviation (e.g., US) */,\n  \"st\" TEXT /* State abbreviation (e.g., AL) */,\n  PRIMARY KEY (\"region_id\")\n)", "CREATE TABLE \"site_regions\" (\n  \"site_id\" INTEGER /* Foreign key referencing the monitoring_sites table */,\n  \"region_id\" INTEGER /* Foreign key referencing the regions table */,\n  PRIMARY KEY (\"site_id\", \"region_id\")\n)"], "column_names": [[-1, "*"], [0, "Unique identifier for each attribute record"], [0, "Foreign key referencing the monitoring_sites table"], [0, "Name of the attribute being tracked"], [0, "Value of the attribute at a specific point in time"], [0, "Timestamp indicating when the attribute value was recorded"], [0, "Unit of measurement for the attribute value"], [1, "Unique identifier for each reading record"], [1, "Foreign key referencing the monitoring_sites table"], [1, "Timestamp indicating when the reading was taken"], [1, "Parameter being measured"], [1, "Value of the parameter at the time of the reading"], [1, "Unit of measurement for the parameter value"], [2, "Unique identifier for each region"], [2, "Name of the region"], [2, "Brief description of the region"], [2, "Country abbreviation (e.g., US)"], [2, "State abbreviation (e.g., AL)"], [3, "Foreign key referencing the monitoring_sites table"], [3, "Foreign key referencing the regions table"]], "column_names_original": [[-1, "*"], [0, "attribute_id"], [0, "site_id"], [0, "attribute_name"], [0, "attribute_value"], [0, "recorded_at"], [0, "units"], [1, "reading_id"], [1, "site_id"], [1, "reading_date"], [1, "parameter"], [1, "value"], [1, "units"], [2, "region_id"], [2, "region_name"], [2, "description"], [2, "ct"], [2, "st"], [3, "site_id"], [3, "region_id"]], "column_types": ["text", "INTEGER", "INTEGER", "TEXT", "TEXT", "TEXT", "TEXT", "INTEGER", "INTEGER", "TEXT", "TEXT", "TEXT", "TEXT", "INTEGER", "TEXT", "TEXT", "TEXT", "TEXT", "INTEGER", "INTEGER"], "table_names": ["site_attributes", "site_readings", "regions", "site_regions"], "table_names_original": ["site_attributes", "site_readings", "regions", "site_regions"], "foreign_keys": [], "primary_keys": [1, 7, 13, 18]}